setup.py
iProxyPool/__init__.py
iProxyPool.egg-info/PKG-INFO
iProxyPool.egg-info/SOURCES.txt
iProxyPool.egg-info/dependency_links.txt
iProxyPool.egg-info/top_level.txt