Metadata-Version: 1.0
Name: iProxyPool
Version: 0.0.2
Summary: Interface of ProxyPool
Home-page: UNKNOWN
Author: ZVampirEM
Author-email: ZVampirEM77@163.com
License: MIT License
Keywords: iProxyPool
Platform: any
